{
  "id": "s_1",
  "name": "Первые шаги под землю",
  "description": "Базовый сценарий для обучения.",
  "halls": [
    {"id": "prison", "connections": ["potion_masters_hall"], "tokens": ["treasury_2"]},
    {"id": "potion_masters_hall", "connections": ["prison", "treasury"], "tokens": ["treasury_3"]},
    {"id": "treasury", "connections": ["potion_masters_hall", "cabinet", "workshop"], "tokens": ["treasury_4", "closed_portal"]},
    {"id": "cabinet", "connections": ["treasury", "trainers_hall"], "tokens": ["treasury_3"]},
    {"id": "trainers_hall", "connections": ["cabinet", "cemetery"], "tokens": ["treasury_2"]},
    {"id": "cemetery", "connections": ["trainers_hall", "forge"], "tokens": ["treasury_1"]},
    {"id": "forge", "connections": ["cemetery", "library"], "tokens": ["treasury_2", "closed_portal"]},
    {"id": "library", "connections": ["forge", "sewerage"], "tokens": ["treasury_1"]},
    {"id": "sewerage", "connections": ["library", "workshop"], "tokens": ["treasury_2"]},
    {"id": "workshop", "connections": ["sewerage", "treasury"], "tokens": ["treasury_3"]}
  ]
}
